LICENSE
MANIFEST.in
README.md
setup.cfg
setup.py
python/README.md
python/README.rst
python/benchmarks/README.rst
python/fastText/FastText.py
python/fastText/__init__.py
python/fastText/pybind/fasttext_pybind.cc
python/fastText/tests/__init__.py
python/fastText/tests/test_configurations.py
python/fastText/tests/test_script.py
python/fastText/util/__init__.py
python/fastText/util/util.py
python/fasttext_github.egg-info/PKG-INFO
python/fasttext_github.egg-info/SOURCES.txt
python/fasttext_github.egg-info/dependency_links.txt
python/fasttext_github.egg-info/not-zip-safe
python/fasttext_github.egg-info/requires.txt
python/fasttext_github.egg-info/top_level.txt
src/args.cc
src/args.h
src/densematrix.cc
src/densematrix.h
src/dictionary.cc
src/dictionary.h
src/fasttext.cc
src/fasttext.h
src/loss.cc
src/loss.h
src/main.cc
src/matrix.cc
src/matrix.h
src/meter.cc
src/meter.h
src/model.cc
src/model.h
src/productquantizer.cc
src/productquantizer.h
src/quantmatrix.cc
src/quantmatrix.h
src/real.h
src/utils.cc
src/utils.h
src/vector.cc
src/vector.h